autokitteh/__init__.py
autokitteh/activities.py
autokitteh/airtable.py
autokitteh/anthropic.py
autokitteh/asana.py
autokitteh/atlassian.py
autokitteh/attr_dict.py
autokitteh/auth0.py
autokitteh/aws.py
autokitteh/azurebot.py
autokitteh/connections.py
autokitteh/discord.py
autokitteh/errors.py
autokitteh/event.py
autokitteh/events.py
autokitteh/github.py
autokitteh/google.py
autokitteh/hubspot.py
autokitteh/kubernetes.py
autokitteh/linear.py
autokitteh/microsoft.py
autokitteh/notion.py
autokitteh/oauth2_session.py
autokitteh/openai.py
autokitteh/outcomes.py
autokitteh/packages.py
autokitteh/pipedrive.py
autokitteh/py.typed
autokitteh/reddit.py
autokitteh/salesforce.py
autokitteh/signals.py
autokitteh/slack.py
autokitteh/slack_test.py
autokitteh/store.py
autokitteh/telegram.py
autokitteh/triggers.py
autokitteh/twilio.py
autokitteh/zoom.py
autokitteh-0.8.2.dist-info/licenses/LICENSE
autokitteh-0.8.2.dist-info/METADATA
autokitteh-0.8.2.dist-info/WHEEL
autokitteh-0.8.2.dist-info/top_level.txt
autokitteh-0.8.2.dist-info/RECORD
