Metadata-Version: 2.4
Name: autokitteh
Version: 0.8.2
Summary: AutoKitteh Python SDK
License:                                  Apache License
Requires-Python: >=3.11
License-File: LICENSE
Provides-Extra: all
Requires-Dist: anthropic~=0.75.0; extra == "all"
Requires-Dist: asana~=5.0; extra == "all"
Requires-Dist: atlassian-python-api~=3.41; extra == "all"
Requires-Dist: auth0-python~=4.7; extra == "all"
Requires-Dist: azure-identity~=1.19; extra == "all"
Requires-Dist: boto3~=1.35; extra == "all"
Requires-Dist: discord.py~=2.5; extra == "all"
Requires-Dist: google-api-python-client~=2.155; extra == "all"
Requires-Dist: google-auth-httplib2~=0.2; extra == "all"
Requires-Dist: google-auth-oauthlib~=1.2; extra == "all"
Requires-Dist: google-generativeai~=0.8; extra == "all"
Requires-Dist: gspread~=6.2; extra == "all"
Requires-Dist: gspread-formatting~=1.2; extra == "all"
Requires-Dist: hubspot-api-client~=11.1; extra == "all"
Requires-Dist: kubernetes~=31.0; extra == "all"
Requires-Dist: msgraph-sdk~=1.18; extra == "all"
Requires-Dist: notion_client~=2.0; extra == "all"
Requires-Dist: openai~=1.57; extra == "all"
Requires-Dist: pipedrive-python-lib~=1.2; extra == "all"
Requires-Dist: praw~=7.8; extra == "all"
Requires-Dist: pyairtable~=3.1; extra == "all"
Requires-Dist: PyGithub~=2.8.1; extra == "all"
Requires-Dist: python-telegram-bot~=22.0; extra == "all"
Requires-Dist: simple-salesforce~=1.12; extra == "all"
Requires-Dist: slack-sdk~=3.33; extra == "all"
Requires-Dist: twilio~=9.4; extra == "all"
Requires-Dist: beautifulsoup4~=4.12; extra == "all"
Requires-Dist: grpcio~=1.68; extra == "all"
Requires-Dist: grpcio-reflection~=1.68; extra == "all"
Requires-Dist: pydantic-ai~=1.30; extra == "all"
Requires-Dist: PyYAML~=6.0; extra == "all"
Requires-Dist: requests~=2.32; extra == "all"
Requires-Dist: requests-toolbelt~=1.0; extra == "all"
Requires-Dist: tenacity~=9.0; extra == "all"
Provides-Extra: dev
Requires-Dist: ruff~=0.7; extra == "dev"
Requires-Dist: pytest~=8.3; extra == "dev"
Dynamic: license-file
